sword3common/__init__.py
sword3common/constants.py
sword3common/exceptions.py
sword3common/version.py
sword3common/lib/__init__.py
sword3common/lib/disposition.py
sword3common/lib/seamless.py
sword3common/models/__init__.py
sword3common/models/byreference.py
sword3common/models/error-old.py
sword3common/models/error.py
sword3common/models/mdbr.py
sword3common/models/metadata.py
sword3common/models/segemented_upload.py
sword3common/models/service.py
sword3common/models/status.py
sword3common/test/__init__.py
sword3common/test/fixtures/__init__.py
sword3common/test/fixtures/metadata.py
sword3common/test/fixtures/segmented_upload.py
sword3common/test/fixtures/service.py
sword3common/test/fixtures/status.py
sword3common/test/unit/__init__.py
sword3common/test/unit/test_disposition.py
sword3common/test/unit/test_metadata.py
sword3common/test/unit/test_service.py
sword3common/test/unit/test_status.py
sword3common-0.1.1.dist-info/METADATA
sword3common-0.1.1.dist-info/WHEEL
sword3common-0.1.1.dist-info/top_level.txt
sword3common-0.1.1.dist-info/RECORD
