Metadata-Version: 2.1
Name: sword3common
Version: 0.1.1
Summary: SWORDv3 Common Object Library
Home-page: https://github.com/cottagelabs/sword3-common.py
Author: Cottage Labs
Author-email: richard@cottagelabs.com
License: Apache2
Platform: UNKNOWN
Provides-Extra: docs
Requires-Dist: Sphinx ; extra == 'docs'
Requires-Dist: sphinx-autodoc-annotation ; extra == 'docs'
Provides-Extra: test
Requires-Dist: nose ; extra == 'test'
